rapt_ble/__init__.py
rapt_ble/parser.py
rapt_ble/py.typed
rapt_ble-0.1.1.dist-info/LICENSE
rapt_ble-0.1.1.dist-info/METADATA
rapt_ble-0.1.1.dist-info/WHEEL
rapt_ble-0.1.1.dist-info/RECORD
