Metadata-Version: 2.1
Name: rapt-ble
Version: 0.1.1
Summary: Parser for the RAPT Pill hydrometer BLE packets.
Home-page: https://github.com/sairon/rapt-ble
License: MIT
Author: Jan Čermák
Author-email: sairon@sairon.cz
Requires-Python: >=3.9,<4.0
Classifier: Development Status :: 2 - Pre-Alpha
Classifier: Intended Audience :: Developers
Classifier: License :: OSI Approved :: MIT License
Classifier: Natural Language :: English
Classifier: Operating System :: OS Independent
Classifier: Programming Language :: Python :: 3
Classifier: Programming Language :: Python :: 3.9
Classifier: Programming Language :: Python :: 3.10
Classifier: Programming Language :: Python :: 3.11
Classifier: Topic :: Software Development :: Libraries
Requires-Dist: bluetooth-data-tools (>=0.3.1)
Requires-Dist: bluetooth-sensor-state-data (>=1.6.1)
Requires-Dist: home-assistant-bluetooth (>=1.9.2)
Requires-Dist: sensor-state-data (>=2.13.0)
Project-URL: Bug Tracker, https://github.com/sairon/rapt-ble/issues
Project-URL: Changelog, https://github.com/sairon/rapt-ble/blob/main/CHANGELOG.md
Project-URL: Documentation, https://rapt-ble.readthedocs.io
Project-URL: Repository, https://github.com/sairon/rapt-ble
